protovtor/__init__.py
protovtor/fields.py
protovtor/protocol.py
protovtor/validators.py
protovtor-1.0.1.dist-info/METADATA
protovtor-1.0.1.dist-info/RECORD
protovtor-1.0.1.dist-info/WHEEL
protovtor-1.0.1.dist-info/top_level.txt
