Metadata-Version: 2.1
Name: protovtor
Version: 1.0.1
Summary: Simple data conversion and validation library
Home-page: https://github.com/konglwbox/protovtor
Author: konglw
Author-email: konglwbox@foxmail.com
License: MIT
Keywords: protovtor,json,conversion,validation
Platform: UNKNOWN
Requires-Python: >=2.7
